postleaks/__init__.py
postleaks/__main__.py
postleaks/config.yml
postleaks-1.1.6.dist-info/LICENSE
postleaks-1.1.6.dist-info/METADATA
postleaks-1.1.6.dist-info/WHEEL
postleaks-1.1.6.dist-info/entry_points.txt
postleaks-1.1.6.dist-info/top_level.txt
postleaks-1.1.6.dist-info/RECORD
