Metadata-Version: 2.1
Name: postleaks
Version: 1.1.6
Summary: Postleaks
Home-page: https://github.com/cosad3s/postleaks
Author: Sébastien Copin
Author-email: cosad3s@outlook.com
License: GPL-3.0 License
Keywords: leaks,postman,osint,bugbounty
Classifier: Topic :: Internet :: WWW/HTTP :: Indexing/Search
Classifier: Topic :: Security
Classifier: Programming Language :: Python :: 3
License-File: LICENSE
Requires-Dist: argparse
Requires-Dist: requests
Requires-Dist: whispers>=2.2.1
